{
  "topBlocked": [
    {
      "name": "googleads.g.doubleclick.net",
      "count": 16
    },
    {
      "name": "www.googletagmanager.com",
      "count": 12
    },
    {
      "name": "assets.adobedtm.com",
      "count": 12
    },
    {
      "name": "cdn.branch.io",
      "count": 7
    },
    {
      "name": "cdn.tinypass.com",
      "count": 6
    },
    {
      "name": "www.google-analytics.com",
      "count": 6
    },
    {
      "name": "api3.branch.io",
      "count": 5
    },
    {
      "name": "gslb-2.demdex.net",
      "count": 4
    },
    {
      "name": "dpm.demdex.net",
      "count": 4
    },
    {
      "name": "securepubads.g.doubleclick.net",
      "count": 3
    }
  ],
  "topBlockedNormalized": [
    {
      "name": "doubleclick.net",
      "count": 35
    },
    {
      "name": "googletagmanager.com",
      "count": 15
    },
    {
      "name": "adobedtm.com",
      "count": 12
    },
    {
      "name": "branch.io",
      "count": 12
    },
    {
      "name": "demdex.net",
      "count": 10
    },
    {
      "name": "tinypass.com",
      "count": 6
    },
    {
      "name": "google-analytics.com",
      "count": 6
    },
    {
      "name": "adnxs.com",
      "count": 5
    },
    {
      "name": "wp.com",
      "count": 3
    },
    {
      "name": "google.com",
      "count": 3
    }
  ],
  "totals": {
    "blocked": 107,
    "allowed": 5893
  },
  "topQueries": [
    {
      "name": "www.cloudflarestatus.com",
      "count": 141
    },
    {
      "name": "time.cloudflare.com",
      "count": 135
    },
    {
      "name": "p2p-sea1.discovery.steamserver.net",
      "count": 116
    },
    {
      "name": "canary.discord.com",
      "count": 113
    },
    {
      "name": "cdn.discordapp.com",
      "count": 105
    },
    {
      "name": "guc3-spclient.spotify.com",
      "count": 104
    },
    {
      "name": "spclient.wg.spotify.com",
      "count": 88
    },
    {
      "name": "www.msftconnecttest.com",
      "count": 76
    },
    {
      "name": "ipv6.msftncsi.com",
      "count": 72
    },
    {
      "name": "www.msftncsi.com",
      "count": 70
    }
  ],
  "topBlockedTotals": [
    {
      "name": "googleads.g.doubleclick.net",
      "blockedCount": 16,
      "totalCount": 16
    },
    {
      "name": "www.googletagmanager.com",
      "blockedCount": 12,
      "totalCount": 12
    },
    {
      "name": "assets.adobedtm.com",
      "blockedCount": 12,
      "totalCount": 12
    },
    {
      "name": "cdn.branch.io",
      "blockedCount": 7,
      "totalCount": 7
    },
    {
      "name": "cdn.tinypass.com",
      "blockedCount": 6,
      "totalCount": 6
    },
    {
      "name": "www.google-analytics.com",
      "blockedCount": 6,
      "totalCount": 6
    },
    {
      "name": "api3.branch.io",
      "blockedCount": 5,
      "totalCount": 5
    },
    {
      "name": "gslb-2.demdex.net",
      "blockedCount": 4,
      "totalCount": 5
    },
    {
      "name": "dpm.demdex.net",
      "blockedCount": 4,
      "totalCount": 6
    },
    {
      "name": "securepubads.g.doubleclick.net",
      "blockedCount": 3,
      "totalCount": 3
    }
  ],
  "topBlockedNormalizedTotals": [
    {
      "name": "doubleclick.net",
      "blockedCount": 35,
      "totalCount": 38
    },
    {
      "name": "googletagmanager.com",
      "blockedCount": 15,
      "totalCount": 15
    },
    {
      "name": "adobedtm.com",
      "blockedCount": 12,
      "totalCount": 12
    },
    {
      "name": "branch.io",
      "blockedCount": 12,
      "totalCount": 12
    },
    {
      "name": "demdex.net",
      "blockedCount": 10,
      "totalCount": 14
    },
    {
      "name": "tinypass.com",
      "blockedCount": 6,
      "totalCount": 6
    },
    {
      "name": "google-analytics.com",
      "blockedCount": 6,
      "totalCount": 6
    },
    {
      "name": "adnxs.com",
      "blockedCount": 5,
      "totalCount": 5
    },
    {
      "name": "wp.com",
      "blockedCount": 3,
      "totalCount": 3
    },
    {
      "name": "google.com",
      "blockedCount": 3,
      "totalCount": 302
    }
  ],
  "blockedSamples": [
    {
      "domain": "stats.g.doubleclick.net",
      "timestamp": "2026-02-08T00:16:04.000Z",
      "decision": "blockedRule",
      "action": null
    },
    {
      "domain": "securepubads.g.doubleclick.net",
      "timestamp": "2026-02-08T00:16:04.000Z",
      "decision": "blockedRule",
      "action": null
    },
    {
      "domain": "pubads.g.doubleclick.net",
      "timestamp": "2026-02-08T00:16:04.000Z",
      "decision": "blockedRule",
      "action": null
    },
    {
      "domain": "googleads4.g.doubleclick.net",
      "timestamp": "2026-02-08T00:16:04.000Z",
      "decision": "blockedRule",
      "action": null
    },
    {
      "domain": "googleads.g.doubleclick.net",
      "timestamp": "2026-02-08T00:16:04.000Z",
      "decision": "blockedRule",
      "action": null
    },
    {
      "domain": "cm.g.doubleclick.net",
      "timestamp": "2026-02-08T00:16:04.000Z",
      "decision": "blockedRule",
      "action": null
    },
    {
      "domain": "gslb-2.demdex.net",
      "timestamp": "2026-02-08T00:16:04.000Z",
      "decision": "blockedRule",
      "action": null
    },
    {
      "domain": "dpm.demdex.net",
      "timestamp": "2026-02-08T00:16:04.000Z",
      "decision": "blockedRule",
      "action": null
    },
    {
      "domain": "ib.adnxs.com",
      "timestamp": "2026-02-08T00:16:04.000Z",
      "decision": "blockedRule",
      "action": null
    },
    {
      "domain": "ib.anycast.adnxs.com",
      "timestamp": "2026-02-08T00:16:04.000Z",
      "decision": "blockedRule",
      "action": null
    },
    {
      "domain": "cdn.tinypass.com",
      "timestamp": "2026-02-08T00:16:03.000Z",
      "decision": "blockedRule",
      "action": null
    },
    {
      "domain": "www.googletagmanager.com",
      "timestamp": "2026-02-08T00:16:02.000Z",
      "decision": "blockedRule",
      "action": null
    },
    {
      "domain": "stats.wp.com",
      "timestamp": "2026-02-08T00:16:02.000Z",
      "decision": "blockedRule",
      "action": null
    },
    {
      "domain": "assets.adobedtm.com",
      "timestamp": "2026-02-08T00:04:58.000Z",
      "decision": "blockedRule",
      "action": null
    },
    {
      "domain": "bid.g.doubleclick.net",
      "timestamp": "2026-02-07T00:13:59.000Z",
      "decision": "blockedRule",
      "action": null
    },
    {
      "domain": "dart.l.doubleclick.net",
      "timestamp": "2026-02-07T00:13:55.000Z",
      "decision": "blockedRule",
      "action": null
    },
    {
      "domain": "adservice.google.com",
      "timestamp": "2026-02-07T00:13:55.000Z",
      "decision": "blockedRule",
      "action": null
    },
    {
      "domain": "cdn.branch.io",
      "timestamp": "2026-02-06T00:08:08.000Z",
      "decision": "blockedRule",
      "action": null
    },
    {
      "domain": "api3.branch.io",
      "timestamp": "2026-02-06T00:08:06.000Z",
      "decision": "blockedRule",
      "action": null
    },
    {
      "domain": "googletagmanager.com",
      "timestamp": "2026-02-06T00:07:06.000Z",
      "decision": "blockedRule",
      "action": null
    },
    {
      "domain": "www.google-analytics.com",
      "timestamp": "2026-02-01T23:57:37.000Z",
      "decision": "blockedRule",
      "action": null
    },
    {
      "domain": "static.doubleclick.net",
      "timestamp": "2026-02-01T23:54:32.000Z",
      "decision": "blockedRule",
      "action": null
    }
  ],
  "meta": {
    "originalRangeKey": "7d",
    "originalRangeLabel": "Last 7 days",
    "requestedRangeKey": "7d",
    "requestedRangeLabel": "Last 7 days",
    "effectiveRangeKey": "7d",
    "effectiveRangeLabel": "Last ~6 days",
    "segmentsPlanned": 7,
    "segmentsAttempted": 7,
    "segmentsSucceeded": 6,
    "segmentsFailed": 1,
    "fallbackUsed": false,
    "messages": [
      "Segment 1/7 – range 7d (from=2026-02-07T00:17:47.000Z, to=2026-02-08T00:17:47.000Z)",
      "Segment 1 returned 1000 logs (accumulated 1000).",
      "Segment 2/7 – range 7d (from=2026-02-06T00:17:47.000Z, to=2026-02-07T00:17:47.000Z)",
      "Segment 2 returned 1000 logs (accumulated 2000).",
      "Segment 3/7 – range 7d (from=2026-02-05T00:17:47.000Z, to=2026-02-06T00:17:47.000Z)",
      "Segment 3 returned 1000 logs (accumulated 3000).",
      "Segment 4/7 – range 7d (from=2026-02-04T00:17:47.000Z, to=2026-02-05T00:17:47.000Z)",
      "Segment 4 returned 1000 logs (accumulated 4000).",
      "Segment 5/7 – range 7d (from=2026-02-03T00:17:47.000Z, to=2026-02-04T00:17:47.000Z)",
      "Segment 5 returned 1000 logs (accumulated 5000).",
      "Segment 6/7 – range 7d (from=2026-02-02T00:17:47.000Z, to=2026-02-03T00:17:47.000Z)",
      "Segment 6 failed: Cloudflare API 500 {\"result\":null,\"success\":false,\"errors\":[{\"code\":1000,\"message\":\"access_resolver.analytics.api.error.ch_query_failed\"}],\"messages\":null}",
      "Segment 7/7 – range 7d (from=2026-02-01T00:17:47.000Z, to=2026-02-02T00:17:47.000Z)",
      "Segment 7 returned 1000 logs (accumulated 6000).",
      "Completed range 7d: gathered 6000 logs."
    ],
    "totalLogs": 6000,
    "fetchedAt": 1770509900066,
    "fetchedAtIso": "2026-02-08T00:18:20.066Z",
    "fetchedCount": 906,
    "fetchedBlocked": 107
  }
}